dgio/__init__.py
dgio/__main__.py
dgio/_version.py
dgio/core.py
dgio/py.typed
dgio-0.0.1.dist-info/LICENSE
dgio-0.0.1.dist-info/WHEEL
dgio-0.0.1.dist-info/METADATA
dgio-0.0.1.dist-info/RECORD
