Metadata-Version: 2.1
Name: dgio
Version: 0.0.1
Summary: Dynamic Graphics IO
Author: jessekrubin
Author-email: jessekrubin@gmail.com
Requires-Python: >=3.6.1,<4.0.0
Classifier: Programming Language :: Python :: 3
Classifier: Programming Language :: Python :: 3.7
Classifier: Programming Language :: Python :: 3.8
